quanttide_data/__init__.py
quanttide_data/crawlers.py
quanttide_data/processors.py
quanttide_data-0.1.0.dist-info/LICENSE
quanttide_data-0.1.0.dist-info/METADATA
quanttide_data-0.1.0.dist-info/WHEEL
quanttide_data-0.1.0.dist-info/RECORD
